callback_lru_cache/__init__.py
callback_lru_cache/lru_cache.py
callback_lru_cache-0.0.7.dist-info/METADATA
callback_lru_cache-0.0.7.dist-info/WHEEL
callback_lru_cache-0.0.7.dist-info/top_level.txt
callback_lru_cache-0.0.7.dist-info/RECORD
