Metadata-Version: 2.1
Name: callback-lru-cache
Version: 0.0.7
Summary: LRU Cache with eviction callback
Home-page: https://github.com/yabqiu/callback-lru-cache
Author: Yanbin
Author-email: yabqiu@gmail.com
License: BSD License
Platform: all
Classifier: Programming Language :: Python :: 3
Classifier: Programming Language :: Python :: 3.6
Classifier: Programming Language :: Python :: 3.7
Classifier: Programming Language :: Python :: 3.8
Classifier: Programming Language :: Python :: 3.9
Classifier: Programming Language :: Python :: 3.10
Classifier: Programming Language :: Python :: Implementation :: CPython
Classifier: Programming Language :: Python :: Implementation :: PyPy
Requires-Python: >=3.2
